RobotFrameworkAI/__init__.py
RobotFrameworkAI/ai_interface/AI_Interface.py
RobotFrameworkAI/ai_interface/__init__.py
RobotFrameworkAI/ai_interface/ai_model_services/AIModelStrategy.py
RobotFrameworkAI/ai_interface/ai_model_services/AIModelTool.py
RobotFrameworkAI/ai_interface/ai_model_services/GeminiService.py
RobotFrameworkAI/ai_interface/ai_model_services/OpenAIService.py
RobotFrameworkAI/ai_interface/ai_model_services/__init__.py
RobotFrameworkAI/ai_interface/ai_model_services/openai_tools/OpenAIAssistant.py
RobotFrameworkAI/ai_interface/ai_model_services/openai_tools/OpenAITextGenerator.py
RobotFrameworkAI/ai_interface/ai_model_services/openai_tools/OpenAITool.py
RobotFrameworkAI/ai_interface/ai_model_services/openai_tools/__init__.py
RobotFrameworkAI/ai_interface/ai_model_tools/AIToolType.py
RobotFrameworkAI/ai_interface/ai_model_tools/AssistantTool.py
RobotFrameworkAI/ai_interface/ai_model_tools/TextGeneratorTool.py
RobotFrameworkAI/ai_interface/ai_model_tools/__init__.py
RobotFrameworkAI/logger/__init__.py
RobotFrameworkAI/logger/logger.py
RobotFrameworkAI/logger/ascii/__init__.py
RobotFrameworkAI/logger/ascii/ascii.misc
RobotFrameworkAI/logger/ascii/ascii.py
RobotFrameworkAI/modules/Module.py
RobotFrameworkAI/modules/__init__.py
RobotFrameworkAI/modules/assistant/Assistant.py
RobotFrameworkAI/modules/assistant/__init__.py
RobotFrameworkAI/modules/chatbot/Chatbot.py
RobotFrameworkAI/modules/chatbot/__init__.py
RobotFrameworkAI/modules/real_test_data_generator/RealTestDataGenerator.py
RobotFrameworkAI/modules/real_test_data_generator/__init__.py
RobotFrameworkAI/modules/real_test_data_generator/test_data_generators/AddressGenerator.py
RobotFrameworkAI/modules/real_test_data_generator/test_data_generators/TestDataGenerator.py
RobotFrameworkAI/modules/real_test_data_generator/test_data_generators/UserDataGenerator.py
RobotFrameworkAI/modules/real_test_data_generator/test_data_generators/__init__.py
RobotFrameworkAI/objects/__init__.py
robotframework_ai-0.0.3.dist-info/LICENSE
robotframework_ai-0.0.3.dist-info/METADATA
robotframework_ai-0.0.3.dist-info/WHEEL
robotframework_ai-0.0.3.dist-info/top_level.txt
robotframework_ai-0.0.3.dist-info/RECORD
